[{
  "姓名":"Bob",
  "证件号":"110116199204015678",
  "民族": "汉",
  "性别":"男",
  "出生日期":"1992年4月1日",
  "住址":"郑州市金水区花园路200号",
  "银行卡号":"622991116400066409",
  "航班时间":"2019-01-20",
  "航班地点":"上海-北京",
  "班次":"T2601",
  "登机口":"32A",
  "航站楼":"T2",
  "座位号":"12-B",
  "舱位":"FA",
  "车牌":"豫AB1122",
  "车辆类型":"小型轿车",
  "检查类型":"血常规+C反应蛋白",
  "检查内容":"白细胞、中性粒细胞、C反应蛋白均偏高",
  "诊断提示":"细菌性上呼吸道感染",
  "药物治疗":"阿莫西林",
  "报告医生":"李红梅",
  "财务状况":"个人从海外网购奢侈品品牌皮包1个，应纳税额3232元",
  "岗位工资":"8000",
  "综合补贴":"2000",
  "年终奖":"2000",
  "同框关系":"同事"
}]